polars_st-0.4.3.dist-info/METADATA
polars_st-0.4.3.dist-info/WHEEL
polars_st-0.4.3.dist-info/licenses/COPYING
polars_st/__init__.py
polars_st/_lib.abi3.so
polars_st/_lib.pyi
polars_st/casting.py
polars_st/conftest.py
polars_st/geodataframe.py
polars_st/geoexpr.py
polars_st/geolazyframe.py
polars_st/geometry.py
polars_st/geoseries.py
polars_st/input.py
polars_st/parsing.py
polars_st/py.typed
polars_st/selectors.py
polars_st/sugar.py
polars_st/typing.py
polars_st/utils/__init__.py
polars_st/utils/internal.py
polars_st/utils/namespace.py
polars_st/utils/srid.py
polars_st-0.4.3.dist-info/RECORD
