Metadata-Version: 2.4
Name: polars-st
Version: 0.4.3
Requires-Dist: polars>=1.34.0
Requires-Dist: pyarrow>=19.0.1
Requires-Dist: pyogrio>=0.9.0
License-File: COPYING
Summary: Spatial extension for Polars DataFrames
License: LGPL-2.1
Requires-Python: >=3.10
Project-URL: Homepage, https://github.com/Oreilles/polars-st
Project-URL: Documentation, https://oreilles.github.io/polars-st/
Project-URL: Issues, https://github.com/Oreilles/polars-st/issues
